bin/__init__.py
bin/find_contaminations.py
bin/generate_config.py
bin/prepare_data.py
bin/winston_find_contaminations.py
bin/winston_prepare_data.py
config/__init__.py
config/settings.yml.default
winston/__init__.py
winston/blast_histogram.py
winston/blast_hit.py
winston/blaster.py
winston/contaminations_finder.py
winston/coverage_detector.py
winston/data_manager.py
winston/mapper.py
winston/name_converter.py
winston/path_resolver.py
winston/seq_id.py
winston/settings.py
winston/types_manager.py
winston/utils.py
winston/blastab/__init__.py
winston/blastab/blastab.py
winston/blastab/one_vs_all.py
winston/blastab/one_vs_one.py
winston/config/__init__.py
winston/config/settings.yml.default
winston_cleaner-0.1.0.dist-info/LICENSE
winston_cleaner-0.1.0.dist-info/METADATA
winston_cleaner-0.1.0.dist-info/WHEEL
winston_cleaner-0.1.0.dist-info/entry_points.txt
winston_cleaner-0.1.0.dist-info/top_level.txt
winston_cleaner-0.1.0.dist-info/RECORD
