Metadata-Version: 2.1
Name: winston-cleaner
Version: 0.1.0
Summary: WinstonCleaner - transcriptomic data cross-contamination eliminator
Home-page: https://github.com/kolecko007/WinstonCleaner
Author: Serafim Nenarokov, Martin Kolisko
Author-email: serafim.nenarokov@gmail.com
License: UNKNOWN
Platform: UNKNOWN
Classifier: Programming Language :: Python :: 2
Classifier: Programming Language :: Python :: 2.7
Classifier: Operating System :: OS Independent
Requires-Python: ==2.7.*
Requires-Dist: matplotlib (==2.0.2)
Requires-Dist: numpy (>=1.14.0)
Requires-Dist: scipy (>=0.19.0)
Requires-Dist: biopython (>=1.68)
Requires-Dist: tqdm (>=4.14.0)
Requires-Dist: pathlib (>=1.0.1)
Requires-Dist: PyYAML (>=3.11)
